yuzhuhwbubbler/__init__.py
yuzhuhwbubbler-0.1.0.dist-info/METADATA
yuzhuhwbubbler-0.1.0.dist-info/WHEEL
yuzhuhwbubbler-0.1.0.dist-info/top_level.txt
yuzhuhwbubbler-0.1.0.dist-info/RECORD
