Metadata-Version: 2.1
Name: yuzhuhwbubbler
Version: 0.1.0
Summary: A bubbler sort package
Home-page: https://github.com/e0431421/bubblewangyuzhu
Author: Yuzhu Wang
Author-email: 15151843600@163.com
License: UNKNOWN
Platform: UNKNOWN
Classifier: Programming Language :: Python :: 3
Classifier: License :: OSI Approved :: MIT License
Classifier: Operating System :: OS Independent
